bruce_li_pro/__init__.py
bruce_li_pro/api_integration.py
bruce_li_pro/data_processing.py
bruce_li_pro/utils.py
bruce_li_pro/visualization.py
tests/__init__.py
Bruce_li_pro-0.0.1.dist-info/METADATA
Bruce_li_pro-0.0.1.dist-info/WHEEL
Bruce_li_pro-0.0.1.dist-info/top_level.txt
Bruce_li_pro-0.0.1.dist-info/RECORD
