Metadata-Version: 2.1
Name: Bruce-li-pro
Version: 0.0.1
Summary: 高效数据处理与API集成工具库
Home-page: https://github.com/bruce-li/Bruce_li_pro
Author: Bruce Li
Author-email: bruce.li@example.com
Classifier: Programming Language :: Python :: 3
Classifier: License :: OSI Approved :: MIT License
Classifier: Operating System :: OS Independent
Requires-Python: >=3.8
Requires-Dist: pandas>=1.0
Requires-Dist: numpy>=1.20
Requires-Dist: requests>=2.25
Requires-Dist: matplotlib>=3.0
Provides-Extra: dev
Requires-Dist: pytest>=7.0; extra == "dev"
Requires-Dist: twine>=4.0; extra == "dev"
Requires-Dist: sphinx>=5.0; extra == "dev"
Provides-Extra: full
Requires-Dist: seaborn>=0.11; extra == "full"
Requires-Dist: plotly>=5.0; extra == "full"
